lupin_grognard/__init__.py
lupin_grognard/__main__.py
lupin_grognard/run.py
lupin_grognard/core/__init__.py
lupin_grognard/core/check.py
lupin_grognard/core/cmd.py
lupin_grognard/core/config.py
lupin_grognard/core/git.py
lupin_grognard/core/gitlab.py
lupin_grognard/core/commit/__init__.py
lupin_grognard/core/commit/commit.py
lupin_grognard/core/commit/commit_error.py
lupin_grognard/core/commit/commit_reporter.py
lupin_grognard/core/commit/commit_validator.py
lupin_grognard/core/doc_generator/__init__.py
lupin_grognard/core/doc_generator/changelog.py
lupin_grognard/core/doc_generator/jinja_generator.py
lupin_grognard/core/doc_generator/reviewlog.py
lupin_grognard/core/doc_generator/ros2_docs.py
lupin_grognard/core/tools/__init__.py
lupin_grognard/core/tools/log_utils.py
lupin_grognard/core/tools/utils.py
lupin_grognard/core/tools/ros2/__init__.py
lupin_grognard/core/tools/ros2/interfaces.py
lupin_grognard/core/tools/ros2/package.py
lupin_grognard/core/tools/ros2/parser.py
lupin_grognard/templates/changelog.j2
lupin_grognard/templates/reviewlog.j2
lupin_grognard/templates/rosapi.j2
lupin_grognard-2.3.1.dist-info/METADATA
lupin_grognard-2.3.1.dist-info/WHEEL
lupin_grognard-2.3.1.dist-info/entry_points.txt
lupin_grognard-2.3.1.dist-info/top_level.txt
lupin_grognard-2.3.1.dist-info/RECORD
