Metadata-Version: 2.4
Name: lupin-grognard
Version: 2.3.1
Summary: Lupin linter tool
Keywords: cli,linter
Classifier: Development Status :: 3 - Alpha
Classifier: Intended Audience :: Information Technology
Classifier: Topic :: Software Development :: Quality Assurance
Classifier: Programming Language :: Python :: 3.10
Classifier: License :: OSI Approved :: MIT License
Requires-Python: >=3.10
Requires-Dist: typer[all]>=0.6.1
Requires-Dist: emoji==2.2.0
Requires-Dist: Jinja2>=3.1.2
Requires-Dist: cmakelang==0.6.13
Requires-Dist: PyYAML==6.0.1
Provides-Extra: test
Requires-Dist: pytest==7.1.3; extra == "test"
Requires-Dist: flake8==5.0.4; extra == "test"
